pygame_toolbox/__init__.py
pygame_toolbox/graphics/widgets.py
pygame_toolbox/graphics/__init__.py
pygame_toolbox/tilegame_tools/__init__.py
pygame_toolbox/twoD_toolbox/__init__.py
pygame_toolbox-0.1.2.dist-info/DESCRIPTION.rst
pygame_toolbox-0.1.2.dist-info/METADATA
pygame_toolbox-0.1.2.dist-info/metadata.json
pygame_toolbox-0.1.2.dist-info/RECORD
pygame_toolbox-0.1.2.dist-info/top_level.txt
pygame_toolbox-0.1.2.dist-info/WHEEL
