Metadata-Version: 2.0
Name: pygame-toolbox
Version: 0.1.2
Summary: Tools to help with game development using pygame
